dataoflatestearthquakeindonesia/__init__.py
Indonesia_latestearthquake-0.2.dist-info/LICENSE
Indonesia_latestearthquake-0.2.dist-info/METADATA
Indonesia_latestearthquake-0.2.dist-info/WHEEL
Indonesia_latestearthquake-0.2.dist-info/requirements.txt
Indonesia_latestearthquake-0.2.dist-info/top_level.txt
Indonesia_latestearthquake-0.2.dist-info/RECORD
