Metadata-Version: 2.1
Name: Indonesia-latestearthquake
Version: 0.2
Summary: Package with beautifulsoup4 and requests, from JSON can be used on mobile & web applications
Home-page: https://github.com/gustusbs/latest-earthquake-indonesia
Author: Eko S Wibowo, Gustus
Author-email: gustussitanggang@gmail.com
License: UNKNOWN
Project-URL: Bug Tracker, https://remoteworker.id
Platform: UNKNOWN
Classifier: Programming Language :: Python :: 3
Classifier: License :: OSI Approved :: GNU General Public License v3 (GPLv3)
Classifier: Operating System :: OS Independent
Classifier: Development Status :: 5 - Production/Stable
Requires-Python: >=3.6
License-File: LICENSE
